sstp_server-0.6.0.dist-info/RECORD
sstp_server-0.6.0.dist-info/top_level.txt
sstp_server-0.6.0.dist-info/entry_points.txt
sstp_server-0.6.0.dist-info/WHEEL
sstp_server-0.6.0.dist-info/METADATA
sstp_server-0.6.0.dist-info/LICENSE
sstpd/utils.py
sstpd/sstp.py
sstpd/proxy_protocol.py
sstpd/ppp.py
sstpd/packets.py
sstpd/constants.py
sstpd/codec.cpython-39-x86_64-linux-gnu.so
sstpd/certtool.py
sstpd/address.py
sstpd/__main__.py
sstpd/__init__.py
