Metadata-Version: 2.1
Name: sstp-server
Version: 0.6.0
Summary: Secure Socket Tunneling Protocol (SSTP) VPN server.
Home-page: https://github.com/sorz/sstp-server
Author: Shell Chen
Author-email: me@sorz.org
License: UNKNOWN
Platform: UNKNOWN
Classifier: Development Status :: 3 - Alpha
Classifier: Environment :: Console
Classifier: Programming Language :: Python :: 3 :: Only
Classifier: Topic :: Internet
Classifier: Topic :: Internet :: Proxy Servers
Classifier: License :: OSI Approved :: MIT License
Requires-Python: >=3.4.4
Provides-Extra: uvloop
Requires-Dist: uvloop (>=0.8.0) ; extra == 'uvloop'
